Workbook

Sheet Supuestos
A1: Academia de League of Legends - Supuestos del modelo
A2: Celdas en azul con fondo amarillo = datos que puedes modificar. Todo lo demas se recalcula solo.
A3: Supuesto | B3: Valor | C3: Fuente / comentario
A4: Cobro mensual por alumno (USD) | B4: 15 | C4: Dato del usuario
A5: Alumnos en el mes 1 | B5: 60 | C5: Supuesto: ajustar segun preventa / comunidad
A6: Crecimiento neto mensual de alumnos | B6: 0.15 | C6: Supuesto: altas menos bajas (churn)
A7: Alumnos maximos por coach | B7: 50 | C7: Supuesto: clases grupales + revision de VODs
A8: Numero de coaches | B8: 4 | C8: Dato del usuario
A9: Sueldo por coach (USD por hora) | B9: 20 | C9: Dato del usuario (20 USD). Se asume pago por hora
A10: Horas pagadas por coach al mes | B10: 20 | C10: Supuesto: 5 h/semana. Si los 20 USD son un sueldo MENSUAL fijo, escribe 1
A11: Comision pasarela de pago (% del ingreso) | B11: 0.05 | C11: Supuesto: PayPal/Stripe aprox. 5%
A12: Plataforma y software mensual (USD) | B12: 60 | C12: Supuesto: Discord Nitro, hosting web, herramientas VOD
A13: Marketing mensual (USD) | B13: 150 | C13: Supuesto: anuncios en redes / creadores
A14: Otros gastos mensuales (USD) | B14: 50 | C14: Supuesto: administracion, varios
A15: Tasa de impuesto sobre utilidad | B15: 0 | C15: Supuesto: ajustar segun pais / regimen
A16: Tasa de descuento anual (costo de oportunidad) | B16: 0.12 | C16: Supuesto: rentabilidad minima exigida
A18: Valores calculados
A19: Tasa de descuento mensual | B19: =(1+B16)^(1/12)-1 -> 0.0094887929 | C19: Equivalente mensual de la tasa anual
A20: Capacidad maxima de alumnos | B20: =B7*B8 -> 200 | C20: Coaches x alumnos por coach
A21: Costo mensual total de coaches (USD) | B21: =B8*B9*B10 -> 1600 | C21: Coaches x sueldo x horas
A22: Costos fijos mensuales totales (USD) | B22: =B21+B12+B13+B14 -> 1860 | C22: Coaches + plataforma + marketing + otros
A23: Margen por alumno despues de comision (USD) | B23: =B4*(1-B11) -> 14.25 | C23: Precio - comision

Sheet Inversion
A1: Inversion inicial (mes 0)
A2: Edita los montos en azul. Los imprevistos se calculan como % del subtotal.
A3: Concepto | B3: Monto (USD) | C3: Comentario
A4: Constitucion legal y tramites | B4: 300 | C4: Supuesto
A5: Pagina web / landing de inscripcion | B5: 400 | C5: Supuesto
A6: Branding (logo, overlays, redes) | B6: 150 | C6: Supuesto
A7: Equipo de streaming (microfono, camara) | B7: 450 | C7: Supuesto
A8: Licencias y herramientas iniciales | B8: 200 | C8: Supuesto
A9: Campana de marketing de lanzamiento | B9: 500 | C9: Supuesto
A10: Subtotal | B10: =SUM(B4:B9) -> 2000
A11: % imprevistos | B11: 0.1 | C11: Supuesto: colchon para gastos no previstos
A12: Imprevistos | B12: =B10*B11 -> 200
A13: INVERSION INICIAL TOTAL | B13: =B10+B12 -> 2200

Sheet Flujo de Caja
A1: Flujo de caja proyectado - 24 meses (USD)
A3: Concepto | B3: Mes 0 | C3: Mes 1 | D3: Mes 2 | E3: Mes 3 | F3: Mes 4 | G3: Mes 5 | H3: Mes 6 | I3: Mes 7 | J3: Mes 8 | K3: Mes 9 | L3: Mes 10 | M3: Mes 11 | N3: Mes 12 | O3: Mes 13 | P3: Mes 14 | Q3: Mes 15 | R3: Mes 16 | S3: Mes 17 | T3: Mes 18 | U3: Mes 19 | V3: Mes 20 | W3: Mes 21 | X3: Mes 22 | Y3: Mes 23 | Z3: Mes 24
A4: Alumnos activos | B4: 0 | C4: =MIN(Supuestos!$B$20,Supuestos!$B$5) -> 60 | D4: =MIN(Supuestos!$B$20,ROUND(C4*(1+Supuestos!$B$6),0)) -> 69 | E4: =MIN(Supuestos!$B$20,ROUND(D4*(1+Supuestos!$B$6),0)) -> 79 | F4: =MIN(Supuestos!$B$20,ROUND(E4*(1+Supuestos!$B$6),0)) -> 91 | G4: =MIN(Supuestos!$B$20,ROUND(F4*(1+Supuestos!$B$6),0)) -> 105 | H4: =MIN(Supuestos!$B$20,ROUND(G4*(1+Supuestos!$B$6),0)) -> 121 | I4: =MIN(Supuestos!$B$20,ROUND(H4*(1+Supuestos!$B$6),0)) -> 139 | J4: =MIN(Supuestos!$B$20,ROUND(I4*(1+Supuestos!$B$6),0)) -> 160 | K4: =MIN(Supuestos!$B$20,ROUND(J4*(1+Supuestos!$B$6),0)) -> 184 | ... Z4: =MIN(Supuestos!$B$20,ROUND(Y4*(1+Supuestos!$B$6),0)) -> 200
A5: Ingresos por mensualidades | B5: 0 | C5: =C4*Supuestos!$B$4 -> 900 | D5: =D4*Supuestos!$B$4 -> 1035 | E5: =E4*Supuestos!$B$4 -> 1185 | F5: =F4*Supuestos!$B$4 -> 1365 | G5: =G4*Supuestos!$B$4 -> 1575 | H5: =H4*Supuestos!$B$4 -> 1815 | I5: =I4*Supuestos!$B$4 -> 2085 | J5: =J4*Supuestos!$B$4 -> 2400 | ... Z5: =Z4*Supuestos!$B$4 -> 3000
A6: (-) Comision pasarela | B6: 0 | C6: =-C5*Supuestos!$B$11 -> -45 | D6: =-D5*Supuestos!$B$11 -> -51.75 | E6: =-E5*Supuestos!$B$11 -> -59.25 | F6: =-F5*Supuestos!$B$11 -> -68.25 | G6: =-G5*Supuestos!$B$11 -> -78.75 | H6: =-H5*Supuestos!$B$11 -> -90.75 | I6: =-I5*Supuestos!$B$11 -> -104.25 | J6: =-J5*Supuestos!$B$11 -> -120 | ... Z6: =-Z5*Supuestos!$B$11 -> -150
A7: Ingresos netos | B7: 0 | C7: =C5+C6 -> 855 | D7: =D5+D6 -> 983.25 | E7: =E5+E6 -> 1125.75 | F7: =F5+F6 -> 1296.75 | G7: =G5+G6 -> 1496.25 | H7: =H5+H6 -> 1724.25 | I7: =I5+I6 -> 1980.75 | J7: =J5+J6 -> 2280 | ... Z7: =Z5+Z6 -> 2850
A8: (-) Sueldos coaches | B8: 0 | C8: =-Supuestos!$B$21 -> -1600 | D8: =-Supuestos!$B$21 -> -1600 | E8: =-Supuestos!$B$21 -> -1600 | F8: =-Supuestos!$B$21 -> -1600 | G8: =-Supuestos!$B$21 -> -1600 | H8: =-Supuestos!$B$21 -> -1600 | I8: =-Supuestos!$B$21 -> -1600 | J8: =-Supuestos!$B$21 -> -1600 | ... Z8: =-Supuestos!$B$21 -> -1600
A9: (-) Plataforma y software | B9: 0 | C9: =-Supuestos!$B$12 -> -60 | D9: =-Supuestos!$B$12 -> -60 | E9: =-Supuestos!$B$12 -> -60 | F9: =-Supuestos!$B$12 -> -60 | G9: =-Supuestos!$B$12 -> -60 | H9: =-Supuestos!$B$12 -> -60 | I9: =-Supuestos!$B$12 -> -60 | J9: =-Supuestos!$B$12 -> -60 | ... Z9: =-Supuestos!$B$12 -> -60
A10: (-) Marketing | B10: 0 | C10: =-Supuestos!$B$13 -> -150 | D10: =-Supuestos!$B$13 -> -150 | E10: =-Supuestos!$B$13 -> -150 | F10: =-Supuestos!$B$13 -> -150 | G10: =-Supuestos!$B$13 -> -150 | H10: =-Supuestos!$B$13 -> -150 | I10: =-Supuestos!$B$13 -> -150 | J10: =-Supuestos!$B$13 -> -150 | ... Z10: =-Supuestos!$B$13 -> -150
A11: (-) Otros gastos | B11: 0 | C11: =-Supuestos!$B$14 -> -50 | D11: =-Supuestos!$B$14 -> -50 | E11: =-Supuestos!$B$14 -> -50 | F11: =-Supuestos!$B$14 -> -50 | G11: =-Supuestos!$B$14 -> -50 | H11: =-Supuestos!$B$14 -> -50 | I11: =-Supuestos!$B$14 -> -50 | J11: =-Supuestos!$B$14 -> -50 | ... Z11: =-Supuestos!$B$14 -> -50
A12: Total egresos operativos | B12: 0 | C12: =SUM(C6,C8:C11) -> -1905 | D12: =SUM(D6,D8:D11) -> -1911.75 | E12: =SUM(E6,E8:E11) -> -1919.25 | F12: =SUM(F6,F8:F11) -> -1928.25 | G12: =SUM(G6,G8:G11) -> -1938.75 | H12: =SUM(H6,H8:H11) -> -1950.75 | I12: =SUM(I6,I8:I11) -> -1964.25 | J12: =SUM(J6,J8:J11) -> -1980 | ... Z12: =SUM(Z6,Z8:Z11) -> -2010
A13: Utilidad operativa | B13: 0 | C13: =C7+SUM(C8:C11) -> -1005 | D13: =D7+SUM(D8:D11) -> -876.75 | E13: =E7+SUM(E8:E11) -> -734.25 | F13: =F7+SUM(F8:F11) -> -563.25 | G13: =G7+SUM(G8:G11) -> -363.75 | H13: =H7+SUM(H8:H11) -> -135.75 | I13: =I7+SUM(I8:I11) -> 120.75 | J13: =J7+SUM(J8:J11) -> 420 | ... Z13: =Z7+SUM(Z8:Z11) -> 990
A14: (-) Impuestos | B14: 0 | C14: =-MAX(0,C13)*Supuestos!$B$15 -> 0 | D14: =-MAX(0,D13)*Supuestos!$B$15 -> 0 | E14: =-MAX(0,E13)*Supuestos!$B$15 -> 0 | F14: =-MAX(0,F13)*Supuestos!$B$15 -> 0 | G14: =-MAX(0,G13)*Supuestos!$B$15 -> 0 | H14: =-MAX(0,H13)*Supuestos!$B$15 -> 0 | I14: =-MAX(0,I13)*Supuestos!$B$15 -> 0 | J14: =-MAX(0,J13)*Supuestos!$B$15 -> 0 | ... Z14: =-MAX(0,Z13)*Supuestos!$B$15 -> 0
A15: Flujo operativo neto | B15: 0 | C15: =C13+C14 -> -1005 | D15: =D13+D14 -> -876.75 | E15: =E13+E14 -> -734.25 | F15: =F13+F14 -> -563.25 | G15: =G13+G14 -> -363.75 | H15: =H13+H14 -> -135.75 | I15: =I13+I14 -> 120.75 | J15: =J13+J14 -> 420 | ... Z15: =Z13+Z14 -> 990
A16: (-) Inversion inicial | B16: =-Inversion!$B$13 -> -2200 | C16: 0 | D16: 0 | E16: 0 | F16: 0 | G16: 0 | H16: 0 | I16: 0 | J16: 0 | K16: 0 | L16: 0 | M16: 0 | N16: 0 | O16: 0 | P16: 0 | Q16: 0 | R16: 0 | S16: 0 | T16: 0 | U16: 0 | V16: 0 | W16: 0 | X16: 0 | Y16: 0 | Z16: 0
A17: FLUJO DE CAJA NETO | B17: =B15+B16 -> -2200 | C17: =C15+C16 -> -1005 | D17: =D15+D16 -> -876.75 | E17: =E15+E16 -> -734.25 | F17: =F15+F16 -> -563.25 | G17: =G15+G16 -> -363.75 | H17: =H15+H16 -> -135.75 | I17: =I15+I16 -> 120.75 | ... Z17: =Z15+Z16 -> 990
A18: Flujo de caja acumulado | B18: =B17 -> -2200 | C18: =B18+C17 -> -3205 | D18: =C18+D17 -> -4081.75 | E18: =D18+E17 -> -4816 | F18: =E18+F17 -> -5379.25 | G18: =F18+G17 -> -5743 | H18: =G18+H17 -> -5878.75 | I18: =H18+I17 -> -5758 | J18: =I18+J17 -> -5338 | ... Z18: =Y18+Z17 -> 10274
A20: Mes 0 = puesta en marcha (solo inversion). Verde = vinculo a otra hoja.

Sheet Indicadores
A1: Indicadores de viabilidad economica
A3: Indicador | B3: Valor | C3: Como se interpreta
A4: INVERSION
A5: Inversion inicial (equipos, web, lanzamiento) | B5: =Inversion!$B$13 -> 2200 | C5: Dinero que se desembolsa en el mes 0
A6: Deficit operativo maximo (capital de trabajo) | B6: =MAX(0,-MIN('Flujo de Caja'!$B$18:$Z$18)-Inversion!$B$13) -> 3678.75 | C6: Perdidas de los primeros meses que tambien debes financiar
A7: INVERSION TOTAL REQUERIDA | B7: =MAX(0,-MIN('Flujo de Caja'!$B$18:$Z$18)) -> 5878.75 | C7: Maximo dinero negativo acumulado = lo que necesitas tener disponible
A8: RENTABILIDAD
A9: VAN / VPN (24 meses) | B9: =NPV(Supuestos!$B$19,'Flujo de Caja'!$C$17:$Z$17)+'Flujo de Caja'!$B$17 -> 8073.0409 | C9: > 0: el proyecto crea valor sobre la tasa exigida
A10: TIR mensual | B10: =IFERROR(IRR('Flujo de Caja'!$B$17:$Z$17,0.02),"No calculable") -> 0.075248191 | C10: Rentabilidad mensual del proyecto
A11: TIR anual equivalente | B11: =IFERROR((1+B10)^12-1,"No calculable") -> 1.3883867 | C11: Viable si es mayor que la tasa de descuento anual
A12: Tasa de descuento anual | B12: =Supuestos!$B$16 -> 0.12 | C12: Rentabilidad minima exigida (Supuestos)
A13: Periodo de recuperacion (meses) | B13: =IF(INDEX('Flujo de Caja'!$B$18:$Z$18,1,25)<0,"No recupera en 24 meses",COUNTIF('Flujo de Caja'!$B$18:$Z$18,"<0")) -> 14 | C13: Primer mes en que el flujo acumulado deja de ser negativo
A14: Utilidad acumulada a 24 meses | B14: =INDEX('Flujo de Caja'!$B$18:$Z$18,1,25) -> 10274 | C14: Flujo acumulado al final del mes 24
A15: ROI a 24 meses | B15: =IFERROR(B14/B7,0) -> 1.7476504 | C15: Utilidad acumulada / inversion total requerida
A16: OPERACION
A17: Punto de equilibrio (alumnos/mes) | B17: =ROUNDUP(Supuestos!$B$22/Supuestos!$B$23,0) -> 131 | C17: Alumnos necesarios para cubrir todos los costos mensuales
A18: Capacidad maxima (alumnos) | B18: =Supuestos!$B$20 -> 200 | C18: Si es menor al punto de equilibrio, el negocio NO es viable
A19: Punto de equilibrio en ventas (USD/mes) | B19: =B17*Supuestos!$B$4 -> 1965 | C19: Ingreso mensual minimo
A20: Utilidad mensual a plena capacidad | B20: =B18*Supuestos!$B$23-Supuestos!$B$22 -> 990 | C20: Resultado mensual con la academia llena
A21: Margen a plena capacidad | B21: =IFERROR(B20/(B18*Supuestos!$B$4),0) -> 0.33 | C21: Utilidad / ingresos
A22: CONCLUSION
A23: Dictamen | B23: =IF(AND(ISNUMBER(B9),B9>0,B18>=B17),"VIABLE: VAN positivo y la capacidad supera el punto de equilibrio",IF(B18<B17,"NO VIABLE: la capacidad no alcanza el punto de equilibrio","NO VIABLE en 24 meses: VAN negativo")) -> VIABLE: VAN positivo y la capacidad supera el punto de equilibrio | C23: Resultado automatico segun los supuestos

Sheet Valor Ganado
A1: Indicadores de Valor Ganado (EVM) - Plan del primer ano
A2: Proyecto = inversion + operacion de los meses 1 a 12. Cada mes ingresa en amarillo el % de avance real del plan y el costo real acumulado. Los meses 1-6 traen valores de EJEMPLO: reemplazalos por tus datos.
A4: BAC - Presupuesto total del proyecto (USD) | B4: =F20 -> 25726
A5: Mes de corte (ultimo mes con datos) | B5: =COUNT(D9:D20) -> 6
A8: Mes | B8: % avance planificado | C8: % avance real (dato) | D8: AC - Costo real acumulado (dato) | E8: Egresos planificados del mes | F8: PV - Valor planificado acum. | G8: EV - Valor ganado | H8: CV = EV - AC | I8: SV = EV - PV | J8: CPI = EV / AC | K8: SPI = EV / PV | L8: EAC = BAC / CPI | M8: ETC = EAC - AC | N8: VAC = BAC - EAC | O8: TCPI
A9: 1 | B9: =F9/$B$4 -> 0.1595662 | C9: 0.15 | D9: 4250 | E9: =-'Flujo de Caja'!C12+Inversion!$B$13 -> 4105 | F9: =SUM($E$9:E9) -> 4105 | G9: =IF(D9="","",C9*$B$4) -> 3858.9 | H9: =IF(D9="","",G9-D9) -> -391.1 | I9: =IF(D9="","",G9-F9) -> -246.1 | J9: =IF(D9="","",IFERROR(G9/D9,0)) -> 0.90797647 | K9: =IF(D9="","",IFERROR(G9/F9,0)) -> 0.94004872 | L9: =IF(D9="","",IFERROR($B$4/J9,0)) -> 28333.333 | M9: =IF(D9="","",L9-D9) -> 24083.333 | N9: =IF(D9="","",$B$4-L9) -> -2607.3333 | O9: =IF(D9="","",IFERROR(($B$4-G9)/($B$4-D9),0)) -> 1.018211
A10: 2 | B10: =F10/$B$4 -> 0.23387818 | C10: 0.22 | D10: 6300 | E10: =-'Flujo de Caja'!D12 -> 1911.75 | F10: =SUM($E$9:E10) -> 6016.75 | G10: =IF(D10="","",C10*$B$4) -> 5659.72 | H10: =IF(D10="","",G10-D10) -> -640.28 | I10: =IF(D10="","",G10-F10) -> -357.03 | J10: =IF(D10="","",IFERROR(G10/D10,0)) -> 0.89836825 | K10: =IF(D10="","",IFERROR(G10/F10,0)) -> 0.94066066 | L10: =IF(D10="","",IFERROR($B$4/J10,0)) -> 28636.364 | M10: =IF(D10="","",L10-D10) -> 22336.364 | N10: =IF(D10="","",$B$4-L10) -> -2910.3636 | O10: =IF(D10="","",IFERROR(($B$4-G10)/($B$4-D10),0)) -> 1.03296
A11: 3 | B11: =F11/$B$4 -> 0.30848169 | C11: 0.29 | D11: 8250 | E11: =-'Flujo de Caja'!E12 -> 1919.25 | F11: =SUM($E$9:E11) -> 7936 | G11: =IF(D11="","",C11*$B$4) -> 7460.54 | H11: =IF(D11="","",G11-D11) -> -789.46 | I11: =IF(D11="","",G11-F11) -> -475.46 | J11: =IF(D11="","",IFERROR(G11/D11,0)) -> 0.90430788 | K11: =IF(D11="","",IFERROR(G11/F11,0)) -> 0.94008821 | L11: =IF(D11="","",IFERROR($B$4/J11,0)) -> 28448.276 | M11: =IF(D11="","",L11-D11) -> 20198.276 | N11: =IF(D11="","",$B$4-L11) -> -2722.2759 | O11: =IF(D11="","",IFERROR(($B$4-G11)/($B$4-D11),0)) -> 1.045174
A12: 4 | B12: =F12/$B$4 -> 0.38343505 | C12: 0.37 | D12: 10150 | E12: =-'Flujo de Caja'!F12 -> 1928.25 | F12: =SUM($E$9:E12) -> 9864.25 | G12: =IF(D12="","",C12*$B$4) -> 9518.62 | H12: =IF(D12="","",G12-D12) -> -631.38 | I12: =IF(D12="","",G12-F12) -> -345.63 | J12: =IF(D12="","",IFERROR(G12/D12,0)) -> 0.93779507 | K12: =IF(D12="","",IFERROR(G12/F12,0)) -> 0.96496135 | L12: =IF(D12="","",IFERROR($B$4/J12,0)) -> 27432.432 | M12: =IF(D12="","",L12-D12) -> 17282.432 | N12: =IF(D12="","",$B$4-L12) -> -1706.4324 | O12: =IF(D12="","",IFERROR(($B$4-G12)/($B$4-D12),0)) -> 1.0405354
A13: 5 | B13: =F13/$B$4 -> 0.45879655 | C13: 0.45 | D13: 12100 | E13: =-'Flujo de Caja'!G12 -> 1938.75 | F13: =SUM($E$9:E13) -> 11803 | G13: =IF(D13="","",C13*$B$4) -> 11576.7 | H13: =IF(D13="","",G13-D13) -> -523.3 | I13: =IF(D13="","",G13-F13) -> -226.3 | J13: =IF(D13="","",IFERROR(G13/D13,0)) -> 0.95675207 | K13: =IF(D13="","",IFERROR(G13/F13,0)) -> 0.98082691 | L13: =IF(D13="","",IFERROR($B$4/J13,0)) -> 26888.889 | M13: =IF(D13="","",L13-D13) -> 14788.889 | N13: =IF(D13="","",$B$4-L13) -> -1162.8889 | O13: =IF(D13="","",IFERROR(($B$4-G13)/($B$4-D13),0)) -> 1.0384045
A14: 6 | B14: =F14/$B$4 -> 0.5346245 | C14: 0.52 | D14: 14200 | E14: =-'Flujo de Caja'!H12 -> 1950.75 | F14: =SUM($E$9:E14) -> 13753.75 | G14: =IF(D14="","",C14*$B$4) -> 13377.52 | H14: =IF(D14="","",G14-D14) -> -822.48 | I14: =IF(D14="","",G14-F14) -> -376.23 | J14: =IF(D14="","",IFERROR(G14/D14,0)) -> 0.94207887 | K14: =IF(D14="","",IFERROR(G14/F14,0)) -> 0.97264528 | L14: =IF(D14="","",IFERROR($B$4/J14,0)) -> 27307.692 | M14: =IF(D14="","",L14-D14) -> 13107.692 | N14: =IF(D14="","",$B$4-L14) -> -1581.6923 | O14: =IF(D14="","",IFERROR(($B$4-G14)/($B$4-D14),0)) -> 1.0713587
A15: 7 | B15: =F15/$B$4 -> 0.61097722 | E15: =-'Flujo de Caja'!I12 -> 1964.25 | F15: =SUM($E$9:E15) -> 15718 | G15: =IF(D15="","",C15*$B$4) | H15: =IF(D15="","",G15-D15) | I15: =IF(D15="","",G15-F15) | J15: =IF(D15="","",IFERROR(G15/D15,0)) | K15: =IF(D15="","",IFERROR(G15/F15,0)) | L15: =IF(D15="","",IFERROR($B$4/J15,0)) | M15: =IF(D15="","",L15-D15) | N15: =IF(D15="","",$B$4-L15) | O15: =IF(D15="","",IFERROR(($B$4-G15)/($B$4-D15),0))
A16: 8 | B16: =F16/$B$4 -> 0.68794216 | E16: =-'Flujo de Caja'!J12 -> 1980 | F16: =SUM($E$9:E16) -> 17698 | G16: =IF(D16="","",C16*$B$4) | H16: =IF(D16="","",G16-D16) | I16: =IF(D16="","",G16-F16) | J16: =IF(D16="","",IFERROR(G16/D16,0)) | K16: =IF(D16="","",IFERROR(G16/F16,0)) | L16: =IF(D16="","",IFERROR($B$4/J16,0)) | M16: =IF(D16="","",L16-D16) | N16: =IF(D16="","",$B$4-L16) | O16: =IF(D16="","",IFERROR(($B$4-G16)/($B$4-D16),0))
A17: 9 | B17: =F17/$B$4 -> 0.76560678 | E17: =-'Flujo de Caja'!K12 -> 1998 | F17: =SUM($E$9:E17) -> 19696 | G17: =IF(D17="","",C17*$B$4) | H17: =IF(D17="","",G17-D17) | I17: =IF(D17="","",G17-F17) | J17: =IF(D17="","",IFERROR(G17/D17,0)) | K17: =IF(D17="","",IFERROR(G17/F17,0)) | L17: =IF(D17="","",IFERROR($B$4/J17,0)) | M17: =IF(D17="","",L17-D17) | N17: =IF(D17="","",$B$4-L17) | O17: =IF(D17="","",IFERROR(($B$4-G17)/($B$4-D17),0))
A18: 10 | B18: =F18/$B$4 -> 0.84373785 | E18: =-'Flujo de Caja'!L12 -> 2010 | F18: =SUM($E$9:E18) -> 21706 | G18: =IF(D18="","",C18*$B$4) | H18: =IF(D18="","",G18-D18) | I18: =IF(D18="","",G18-F18) | J18: =IF(D18="","",IFERROR(G18/D18,0)) | K18: =IF(D18="","",IFERROR(G18/F18,0)) | L18: =IF(D18="","",IFERROR($B$4/J18,0)) | M18: =IF(D18="","",L18-D18) | N18: =IF(D18="","",$B$4-L18) | O18: =IF(D18="","",IFERROR(($B$4-G18)/($B$4-D18),0))
A19: 11 | B19: =F19/$B$4 -> 0.92186893 | E19: =-'Flujo de Caja'!M12 -> 2010 | F19: =SUM($E$9:E19) -> 23716 | G19: =IF(D19="","",C19*$B$4) | H19: =IF(D19="","",G19-D19) | I19: =IF(D19="","",G19-F19) | J19: =IF(D19="","",IFERROR(G19/D19,0)) | K19: =IF(D19="","",IFERROR(G19/F19,0)) | L19: =IF(D19="","",IFERROR($B$4/J19,0)) | M19: =IF(D19="","",L19-D19) | N19: =IF(D19="","",$B$4-L19) | O19: =IF(D19="","",IFERROR(($B$4-G19)/($B$4-D19),0))
A20: 12 | B20: =F20/$B$4 -> 1 | E20: =-'Flujo de Caja'!N12 -> 2010 | F20: =SUM($E$9:E20) -> 25726 | G20: =IF(D20="","",C20*$B$4) | H20: =IF(D20="","",G20-D20) | I20: =IF(D20="","",G20-F20) | J20: =IF(D20="","",IFERROR(G20/D20,0)) | K20: =IF(D20="","",IFERROR(G20/F20,0)) | L20: =IF(D20="","",IFERROR($B$4/J20,0)) | M20: =IF(D20="","",L20-D20) | N20: =IF(D20="","",$B$4-L20) | O20: =IF(D20="","",IFERROR(($B$4-G20)/($B$4-D20),0))
A22: Resumen al mes de corte
A23: PV - Valor planificado | B23: =IF($B$5=0,"Sin datos",INDEX(F9:F20,$B$5)) -> 13753.75 | C23: Lo que debias haber gastado/avanzado segun el plan
A24: EV - Valor ganado | B24: =IF($B$5=0,"Sin datos",INDEX(G9:G20,$B$5)) -> 13377.52 | C24: Valor del trabajo realmente completado
A25: AC - Costo real | B25: =IF($B$5=0,"Sin datos",INDEX(D9:D20,$B$5)) -> 14200 | C25: Lo que realmente gastaste
A26: CV - Variacion de costo | B26: =IF($B$5=0,"Sin datos",INDEX(H9:H20,$B$5)) -> -822.48 | C26: > 0 ahorro; < 0 sobrecosto
A27: SV - Variacion de cronograma | B27: =IF($B$5=0,"Sin datos",INDEX(I9:I20,$B$5)) -> -376.23 | C27: > 0 adelantado; < 0 atrasado
A28: CPI - Indice de desempeno de costo | B28: =IF($B$5=0,"Sin datos",INDEX(J9:J20,$B$5)) -> 0.94207887 | C28: >= 1 eficiente en costos
A29: SPI - Indice de desempeno de cronograma | B29: =IF($B$5=0,"Sin datos",INDEX(K9:K20,$B$5)) -> 0.97264528 | C29: >= 1 dentro o adelantado al plan
A30: EAC - Estimacion al terminar | B30: =IF($B$5=0,"Sin datos",INDEX(L9:L20,$B$5)) -> 27307.692 | C30: Costo final esperado si sigue el CPI actual
A31: ETC - Estimacion para completar | B31: =IF($B$5=0,"Sin datos",INDEX(M9:M20,$B$5)) -> 13107.692 | C31: Lo que falta por gastar
A32: VAC - Variacion al terminar | B32: =IF($B$5=0,"Sin datos",INDEX(N9:N20,$B$5)) -> -1581.6923 | C32: > 0 terminara bajo presupuesto
A33: TCPI - Indice de desempeno por completar | B33: =IF($B$5=0,"Sin datos",INDEX(O9:O20,$B$5)) -> 1.0713587 | C33: Eficiencia necesaria para cumplir el BAC
A34: Estado del costo | B34: =IF($B$5=0,"Sin datos",IF(B28>=1,"Bajo presupuesto","Sobre presupuesto")) -> Sobre presupuesto
A35: Estado del cronograma | B35: =IF($B$5=0,"Sin datos",IF(B29>=1,"Adelantado / a tiempo","Atrasado")) -> Atrasado
